aiosumma/__init__.py
aiosumma/cli.py
aiosumma/client.py
aiosumma/context.py
aiosumma/errors.py
aiosumma/eval_scorer_builder.py
aiosumma/processor.py
aiosumma/data/synsets/drugs.csv
aiosumma/parser/__init__.py
aiosumma/parser/elements.py
aiosumma/parser/errors.py
aiosumma/parser/parser.py
aiosumma/parser/tests/__init__.py
aiosumma/parser/tests/test.py
aiosumma/parser/tests/test_parser.py
aiosumma/parser/tests/test_summa_query.py
aiosumma/proto/__init__.py
aiosumma/proto/beacon_service_pb2.py
aiosumma/proto/beacon_service_pb2_grpc.py
aiosumma/proto/consumer_service_pb2.py
aiosumma/proto/consumer_service_pb2_grpc.py
aiosumma/proto/index_service_pb2.py
aiosumma/proto/index_service_pb2_grpc.py
aiosumma/proto/query_pb2.py
aiosumma/proto/query_pb2_grpc.py
aiosumma/proto/reflection_service_pb2.py
aiosumma/proto/reflection_service_pb2_grpc.py
aiosumma/proto/search_service_pb2.py
aiosumma/proto/search_service_pb2_grpc.py
aiosumma/proto/utils_pb2.py
aiosumma/proto/utils_pb2_grpc.py
aiosumma/tests/__init__.py
aiosumma/tests/test.py
aiosumma/tests/test_eval_scorer_builder.py
aiosumma/tests/test_processor.py
aiosumma/tests/test_spellcheck.py
aiosumma/tests/test_synonym.py
aiosumma/tests/test_unmatched_parentheses.py
aiosumma/text_transformers/__init__.py
aiosumma/text_transformers/base.py
aiosumma/text_transformers/clean.py
aiosumma/text_transformers/despace.py
aiosumma/text_transformers/lower.py
aiosumma/text_transformers/unmatched_parentheses.py
aiosumma/tree_transformers/__init__.py
aiosumma/tree_transformers/base.py
aiosumma/tree_transformers/doi.py
aiosumma/tree_transformers/exact_match.py
aiosumma/tree_transformers/field.py
aiosumma/tree_transformers/morphy.py
aiosumma/tree_transformers/optimizing.py
aiosumma/tree_transformers/order_by.py
aiosumma/tree_transformers/spellcheck.py
aiosumma/tree_transformers/synonym.py
aiosumma/tree_transformers/tantivy.py
aiosumma/tree_transformers/values.py
aiosumma_wheel-2.14.0.dist-info/METADATA
aiosumma_wheel-2.14.0.dist-info/WHEEL
aiosumma_wheel-2.14.0.dist-info/entry_points.txt
aiosumma_wheel-2.14.0.dist-info/top_level.txt
aiosumma_wheel-2.14.0.dist-info/RECORD
