Metadata-Version: 2.1
Name: aiosumma-wheel
Version: 2.14.0
Summary: Async client for Summa Search
Author-email: Pasha Podolsky <ppodolsky@me.com>
Project-URL: Homepage, https://github.com/izihawa/aiosumma
Project-URL: Documentation, https://izihawa.github.io/summa
Classifier: Programming Language :: Python :: 3.10
Classifier: Topic :: Internet :: WWW/HTTP :: Indexing/Search
Requires-Python: >=3.10
